four_bit_USR.v
module four_bit_USR (
    input wire clk,
    input wire rst,
    input wire [1:0] mode,
    input wire [3:0] data_in,
    input wire serial_in,
    output reg [3:0] data_out
);

always @(posedge clk or posedge rst) begin
    if (rst)
        data_out <= 4'b0000;
    else begin
        case (mode)
            2'b00: data_out <= data_out; // Hold
            2'b01: data_out <= {serial_in, data_out[3:1]}; // Shift right
            2'b10: data_out <= {data_out[2:0], serial_in}; // Shift left
            2'b11: data_out <= data_in; // Parallel load
        endcase
    end
end

endmodule

tb_four_bit_USR.sv
`timescale 1ns / 1ps

module tb_four_bit_USR;

  reg clk, rst;
  reg [1:0] mode;
  reg [3:0] data_in;
  reg serial_in;
  wire [3:0] data_out;

  // Instantiate the DUT
  four_bit_USR uut (
    .clk(clk),
    .rst(rst),
    .mode(mode),
    .data_in(data_in),
    .serial_in(serial_in),
    .data_out(data_out)
  );

  // Clock Generation
  always #5 clk = ~clk;  // 10ns period

  // Stimulus Task
  task apply_input;
    input [1:0] m;
    input [3:0] din;
    input sin;
    begin
      mode = m;
      data_in = din;
      serial_in = sin;
      #10;
    end
  endtask

  initial begin
    $display("Starting simulation...");
    $dumpfile("waveform.vcd");  // For GTKWAVE
    $dumpvars(0, tb_four_bit_USR);

    clk = 0;
    rst = 1; mode = 0; data_in = 0; serial_in = 0;
    #15 rst = 0;

    // Load 4'b1010
    apply_input(2'b11, 4'b1010, 1'b0);

    // Hold
    apply_input(2'b00, 0, 0);

    // Shift Right with serial in = 1, then 0
    apply_input(2'b01, 0, 1);
    apply_input(2'b01, 0, 0);

    // Shift Left with serial in = 1, then 0
    apply_input(2'b10, 0, 1);
    apply_input(2'b10, 0, 0);

    #20;
    $finish;
  end

endmodule

simulation/modelsim/waveform.vcd
$date
	Wed Apr 30 21:28:59 2025
$end
$version
	ModelSim Version 2020.1
$end
$timescale
	1ps
$end

$scope module tb_four_bit_USR $end
$var reg 1 ! clk $end
$var reg 1 " rst $end
$var reg 2 # mode [1:0] $end
$var reg 4 $ data_in [3:0] $end
$var reg 1 % serial_in $end
$var wire 1 & data_out [3] $end
$var wire 1 ' data_out [2] $end
$var wire 1 ( data_out [1] $end
$var wire 1 ) data_out [0] $end

$scope task apply_input $end
$var reg 2 * m [1:0] $end
$var reg 4 + din [3:0] $end
$var reg 1 , sin $end
$upscope $end

$scope module uut $end
$var wire 1 - clk $end
$var wire 1 . rst $end
$var wire 1 / mode [1] $end
$var wire 1 0 mode [0] $end
$var wire 1 1 data_in [3] $end
$var wire 1 2 data_in [2] $end
$var wire 1 3 data_in [1] $end
$var wire 1 4 data_in [0] $end
$var wire 1 5 serial_in $end
$var reg 4 6 data_out [3:0] $end
$upscope $end
$upscope $end
$enddefinitions $end
#0
$dumpvars
0!
1"
b0 #
b0 $
0%
b0 6
bx *
bx +
x,
0)
0(
0'
0&
0-
1.
00
0/
04
03
02
01
05
$end
#5000
1!
1-
#10000
0!
0-
#15000
0"
b11 *
b1010 +
0,
b11 #
b1010 $
1!
13
11
10
1/
0.
1-
b1010 6
1(
1&
#20000
0!
0-
#25000
b0 *
b0 +
b0 #
b0 $
1!
03
01
00
0/
1-
#30000
0!
0-
#35000
b1 *
1,
b1 #
1%
1!
10
15
1-
b1101 6
1)
0(
1'
#40000
0!
0-
#45000
0,
0%
1!
05
1-
b110 6
0)
1(
0&
#50000
0!
0-
#55000
b10 *
1,
b10 #
1%
1!
00
1/
15
1-
b1101 6
1)
0(
1&
#60000
0!
0-
#65000
0,
0%
1!
05
1-
b1010 6
0)
1(
0'
#70000
0!
0-
#75000
1!
1-
b100 6
0(
1'
0&
#80000
0!
0-
#85000
1!
1-
b1000 6
0'
1&
